{
    "DQN (Standard)": [
        0.0,
        0.0,
        1.0,
        0.0,
        -1.0,
        0.0
    ],
    "SFDQN (Standard)": [
        0.0,
        1.0,
        0.1,
        0.0,
        0.0,
        0.0
    ],
    "FG-SFDQN (alg1)": [
        4.9,
        3.0,
        4.1,
        4.2,
        3.0,
        5.0
    ],
    "FG-SFDQN (alg2)": [
        0.0,
        0.0,
        0.0,
        0.0,
        0.0,
        0.0
    ],
    "FG-SFDQN (alg3)": [
        0.0,
        0.0,
        0.1,
        0.0,
        -0.2,
        0.0
    ]
}
